{
	"dataList":[
		{
			"url":"/static/img/001.jpg",
			"text":"茶叶很棒！手提袋超漂亮的说，而且也很结实，喜庆大气简朴，送礼真是备有面子，我是买来送给我的指导老师的，实习快结束了，送给他一些茶叶，总体来说非常棒！而且快递服务态度也很好！",
			"src":"/static/img/鬼.png",
			"context":"来自用心微笑的评价",
			"title":"武夷岩茶 160g",
			"price":"￥4,288.00"
		},
		{
			"url":"/static/img/002.jpg",
			"text":"茶叶拆开来的时候就闻到一股清淡的茶香味，我就觉得这茶叶一定不错。泡了一杯喝着感觉口感挺浓郁的，这个价位能买到这样的龙井，还是赚到了。日常一天泡个几杯喝没有问题。 下次喝完了再来回购。",
			"src":"/static/img/痴.png",
			"context":"来自淡然无双的评价",
			"title":"龙井 250g",
			"price":"￥188.00"
		},
		{
			"url":"/static/img/003.jpg",
			"text":"包裝特別好，看著很上檔次，這個價位能把包裝做得如此精致，說明很用心。很滿意的一次網購滇红。茶葉很不錯，包裝很精美，剛泡了一泡，茶香口感都很不錯，物有超值。",
			"src":"/static/img/人.png",
			"context":"来自宋嘉榮的评价",
			"title":"云南滇红 100g",
			"price":"￥158.00"
		},
		{
			"url":"/static/img/004.jpg",
			"text":"不错，帮朋友买的，很满意，客服发货很及时，包装很好，已经来买好几次了，老客户了哦，喝完再来味道真不错，昨天剩的一点存货也让朋友拿走了，得抓紧再买点了。",
			"src":"/static/img/鬼.png",
			"context":"来自暮槿的评价",
			"title":"武夷岩茶 48g",
			"price":"￥199.00"
		},
		{
			"url":"/static/img/005.jpg",
			"text":"产品收到泡了一泡先品尝了，份量足，泡出来的茶也是香味浓醇，汤色明净，回味悠长，喝了的家人喜欢，包装仔细严实，很满意的一次购物体验，性价比高，大力推荐！",
			"src":"/static/img/痴.png",
			"context":"来自城院小米的评价",
			"title":"安溪铁观音 240g",
			"price":"￥140.00"
		},
		{
			"url":"/static/img/006.jpg",
			"text":"包装非常的结实，量很足，茶叶叶片非常的饱满整齐，茶香扑鼻，口感醇厚，非常的好喝，既便宜又实惠，物有所值，值得推荐。",
			"src":"/static/img/人.png",
			"context":"来自猫渣子的评价",
			"title":"金骏眉 100g",
			"price":"￥115.00"
		}
		
	]
}
